bidtoolsdk/__init__.py
bidtoolsdk/settings.py
bidtoolsdk/configuration/__init__.py
bidtoolsdk/configuration/adgroup_config.py
bidtoolsdk/google/__init__.py
bidtoolsdk/google/keyword_performance.py
configuration/__init__.py
configuration/dealer_config.py
google/__init__.py
google/keyword_performance.py
test/__init__.py
test/test_config.py
bidtoolsdk-0.0.9.dist-info/METADATA
bidtoolsdk-0.0.9.dist-info/WHEEL
bidtoolsdk-0.0.9.dist-info/top_level.txt
bidtoolsdk-0.0.9.dist-info/RECORD
