Metadata-Version: 2.1
Name: bidtoolsdk
Version: 0.0.9
Summary: bid tool sdk
Home-page: UNKNOWN
Author: UNKNOWN
Author-email: UNKNOWN
License: UNKNOWN
Platform: UNKNOWN
Requires-Dist: pandas (==0.23.4)
Requires-Dist: requests (==2.21.0)
Requires-Dist: python-dotenv (==0.10.1)
